README.md
setup.py
tmpdir.py
tmpdir.egg-info/PKG-INFO
tmpdir.egg-info/SOURCES.txt
tmpdir.egg-info/dependency_links.txt
tmpdir.egg-info/entry_points.txt
tmpdir.egg-info/requires.txt
tmpdir.egg-info/top_level.txt