Metadata-Version: 1.0
Name: tmpdir
Version: 0.0.0.DEV.1308906033
Summary: A module and command line tool for working with temporary directories.
Home-page: https://github.com/jeremybanks/tmpdir
Author: Jeremy Banks
Author-email: jeremy@jeremybanks.ca
License: UNKNOWN
Download-URL: http://pypi.python.org/pypi/tmpdir/0.0.0.DEV.1308906033
Platform: UNKNOWN
Classifier: Programming Language :: Python
Classifier: Programming Language :: Python :: 2.6
Classifier: Programming Language :: Python :: 2.7
Classifier: License :: OSI Approved :: MIT License
Classifier: Development Status :: 2 - Pre-Alpha
Classifier: Intended Audience :: Developers
Classifier: Intended Audience :: End Users/Desktop
Classifier: Environment :: Console
Classifier: Topic :: Utilities
